oakx_robot/__init__.py
oakx_robot/robot_implementation.py
oakx_robot-0.1.0.dist-info/WHEEL
oakx_robot-0.1.0.dist-info/METADATA
oakx_robot-0.1.0.dist-info/RECORD
