Metadata-Version: 2.1
Name: oakx-robot
Version: 0.1.0
Summary: 
Author: cmungall
Author-email: cjm@berkeleybop.org
Requires-Python: >=3.9,<4.0
Classifier: Programming Language :: Python :: 3
Classifier: Programming Language :: Python :: 3.10
Classifier: Programming Language :: Python :: 3.9
Requires-Dist: oaklib (>=0.1.16,<0.2.0)
Requires-Dist: py4j (>=0.10.9,<0.11.0)
